{
  "model_id": "tm_h_c_3_th_ng_h_c_2023_2025_v__0eddb767",
  "summary": {
    "week_2": {
      "quota": "2/tuần",
      "n_trades": 133,
      "trades_per_week": 1.68,
      "win_rate_pct": 63.91,
      "avg_rr": 2.149,
      "profit_factor": 3.537,
      "total_r": 146.458,
      "max_dd_r": 4.5,
      "year_wr_pct": 72.53,
      "year_total_r": 126.698
    },
    "day_1": {
      "quota": "1/ngày",
      "n_trades": 282,
      "trades_per_week": 3.57,
      "win_rate_pct": 51.06,
      "avg_rr": 2.028,
      "profit_factor": 1.914,
      "total_r": 166.934,
      "max_dd_r": 14.57,
      "year_wr_pct": 58.73,
      "year_total_r": 147.419
    }
  },
  "winner": "day_1"
}