{
  "topic": "grade4",
  "words": [
    {
      "word": "address",
      "ipa": "/ˈæˌdrɛs/",
      "phonemes": [
        "æ",
        "d",
        "r",
        "ɛ",
        "s"
      ],
      "meaning": "địa chỉ",
      "emoji": "📍",
      "topic": "grade4",
      "audio_sample_url": ""
    },
    {
      "word": "afternoon",
      "ipa": "/ˌæftərˈnun/",
      "phonemes": [
        "æ",
        "f",
        "t",
        "ə",
        "r",
        "n",
        "u",
        "n"
      ],
      "meaning": "buổi chiều",
      "emoji": "🗓️",
      "topic": "grade4",
      "audio_sample_url": ""
    },
    {
      "word": "animal",
      "ipa": "/ˈænəməl/",
      "phonemes": [
        "æ",
        "n",
        "ə",
        "m",
        "ə",
        "l"
      ],
      "meaning": "động vật",
      "emoji": "🐾",
      "topic": "grade4",
      "audio_sample_url": ""
    },
    {
      "word": "art",
      "ipa": "/ɑrt/",
      "phonemes": [
        "ɑ",
        "r",
        "t"
      ],
      "meaning": "môn Mỹ thuật",
      "emoji": "🎨",
      "topic": "grade4",
      "audio_sample_url": ""
    },
    {
      "word": "art room",
      "ipa": "/ɑrt rum/",
      "phonemes": [
        "ɑ",
        "r",
        "t",
        "r",
        "u",
        "m"
      ],
      "meaning": "phòng mỹ thuật",
      "emoji": "🏙️",
      "topic": "grade4",
      "audio_sample_url": ""
    },
    {
      "word": "Australia",
      "ipa": "/ɔˈstreɪljə/",
      "phonemes": [
        "ɔ",
        "s",
        "t",
        "r",
        "eɪ",
        "l",
        "j",
        "ə"
      ],
      "meaning": "Úc",
      "emoji": "🌏",
      "topic": "grade4",
      "audio_sample_url": ""
    },
    {
      "word": "badminton",
      "ipa": "/ˈbædˌmɪntən/",
      "phonemes": [
        "b",
        "æ",
        "d",
        "m",
        "ɪ",
        "n",
        "t",
        "ə",
        "n"
      ],
      "meaning": "cầu lông",
      "emoji": "🏸",
      "topic": "grade4",
      "audio_sample_url": ""
    },
    {
      "word": "basketball",
      "ipa": "/ˈbæskətˌbɔl/",
      "phonemes": [
        "b",
        "æ",
        "s",
        "k",
        "ə",
        "t",
        "b",
        "ɔ",
        "l"
      ],
      "meaning": "bóng rổ",
      "emoji": "🏀",
      "topic": "grade4",
      "audio_sample_url": ""
    },
    {
      "word": "beach",
      "ipa": "/biʧ/",
      "phonemes": [
        "b",
        "i",
        "ʧ"
      ],
      "meaning": "bãi biển",
      "emoji": "🏖️",
      "topic": "grade4",
      "audio_sample_url": ""
    },
    {
      "word": "beautiful",
      "ipa": "/ˈbjutəfəl/",
      "phonemes": [
        "b",
        "j",
        "u",
        "t",
        "ə",
        "f",
        "ə",
        "l"
      ],
      "meaning": "đẹp",
      "emoji": "🙂",
      "topic": "grade4",
      "audio_sample_url": ""
    },
    {
      "word": "birthday",
      "ipa": "/ˈbərθˌdeɪ/",
      "phonemes": [
        "b",
        "ə",
        "r",
        "θ",
        "d",
        "eɪ"
      ],
      "meaning": "sinh nhật",
      "emoji": "🎉",
      "topic": "grade4",
      "audio_sample_url": ""
    },
    {
      "word": "cake",
      "ipa": "/keɪk/",
      "phonemes": [
        "k",
        "eɪ",
        "k"
      ],
      "meaning": "bánh kem",
      "emoji": "🎂",
      "topic": "grade4",
      "audio_sample_url": ""
    },
    {
      "word": "campfire",
      "ipa": "/ˈkæmpˌfaɪər/",
      "phonemes": [
        "k",
        "æ",
        "m",
        "p",
        "f",
        "aɪ",
        "ə",
        "r"
      ],
      "meaning": "lửa trại",
      "emoji": "🔥",
      "topic": "grade4",
      "audio_sample_url": ""
    },
    {
      "word": "candle",
      "ipa": "/ˈkændəl/",
      "phonemes": [
        "k",
        "æ",
        "n",
        "d",
        "ə",
        "l"
      ],
      "meaning": "nến",
      "emoji": "🕯️",
      "topic": "grade4",
      "audio_sample_url": ""
    },
    {
      "word": "cinema",
      "ipa": "/ˈsɪnəmə/",
      "phonemes": [
        "s",
        "ɪ",
        "n",
        "ə",
        "m",
        "ə"
      ],
      "meaning": "rạp chiếu phim",
      "emoji": "🎦",
      "topic": "grade4",
      "audio_sample_url": ""
    },
    {
      "word": "city",
      "ipa": "/ˈsɪti/",
      "phonemes": [
        "s",
        "ɪ",
        "t",
        "i"
      ],
      "meaning": "thành phố",
      "emoji": "🌆",
      "topic": "grade4",
      "audio_sample_url": ""
    },
    {
      "word": "cloudy",
      "ipa": "/ˈklaʊdi/",
      "phonemes": [
        "k",
        "l",
        "aʊ",
        "d",
        "i"
      ],
      "meaning": "nhiều mây",
      "emoji": "☁️",
      "topic": "grade4",
      "audio_sample_url": ""
    },
    {
      "word": "cold",
      "ipa": "/koʊld/",
      "phonemes": [
        "k",
        "oʊ",
        "l",
        "d"
      ],
      "meaning": "lạnh",
      "emoji": "🌦️",
      "topic": "grade4",
      "audio_sample_url": ""
    },
    {
      "word": "computer room",
      "ipa": "/kəmˈpjutər rum/",
      "phonemes": [
        "k",
        "ə",
        "m",
        "p",
        "j",
        "u",
        "t",
        "ə",
        "r",
        "r",
        "u",
        "m"
      ],
      "meaning": "phòng máy tính",
      "emoji": "🖥️",
      "topic": "grade4",
      "audio_sample_url": ""
    },
    {
      "word": "cook",
      "ipa": "/kʊk/",
      "phonemes": [
        "k",
        "ʊ",
        "k"
      ],
      "meaning": "nấu ăn",
      "emoji": "✅",
      "topic": "grade4",
      "audio_sample_url": ""
    },
    {
      "word": "country",
      "ipa": "/ˈkəntri/",
      "phonemes": [
        "k",
        "ə",
        "n",
        "t",
        "r",
        "i"
      ],
      "meaning": "quốc gia",
      "emoji": "🌐",
      "topic": "grade4",
      "audio_sample_url": ""
    },
    {
      "word": "countryside",
      "ipa": "/ˈkəntriˌsaɪd/",
      "phonemes": [
        "k",
        "ə",
        "n",
        "t",
        "r",
        "i",
        "s",
        "aɪ",
        "d"
      ],
      "meaning": "vùng quê",
      "emoji": "🏞️",
      "topic": "grade4",
      "audio_sample_url": ""
    },
    {
      "word": "crocodile",
      "ipa": "/ˈkrɑkəˌdaɪl/",
      "phonemes": [
        "k",
        "r",
        "ɑ",
        "k",
        "ə",
        "d",
        "aɪ",
        "l"
      ],
      "meaning": "cá sấu",
      "emoji": "🐊",
      "topic": "grade4",
      "audio_sample_url": ""
    },
    {
      "word": "dance",
      "ipa": "/dæns/",
      "phonemes": [
        "d",
        "æ",
        "n",
        "s"
      ],
      "meaning": "nhảy múa",
      "emoji": "💃",
      "topic": "grade4",
      "audio_sample_url": ""
    },
    {
      "word": "do homework",
      "ipa": "/du ˈhoʊmˌwərk/",
      "phonemes": [
        "d",
        "u",
        "h",
        "oʊ",
        "m",
        "w",
        "ə",
        "r",
        "k"
      ],
      "meaning": "làm bài tập",
      "emoji": "📚",
      "topic": "grade4",
      "audio_sample_url": ""
    },
    {
      "word": "doctor",
      "ipa": "/ˈdɔktər/",
      "phonemes": [
        "d",
        "ɔ",
        "k",
        "t",
        "ə",
        "r"
      ],
      "meaning": "bác sĩ",
      "emoji": "🧑‍⚕️",
      "topic": "grade4",
      "audio_sample_url": ""
    },
    {
      "word": "draw",
      "ipa": "/drɔ/",
      "phonemes": [
        "d",
        "r",
        "ɔ"
      ],
      "meaning": "vẽ",
      "emoji": "✅",
      "topic": "grade4",
      "audio_sample_url": ""
    },
    {
      "word": "driver",
      "ipa": "/ˈdraɪvər/",
      "phonemes": [
        "d",
        "r",
        "aɪ",
        "v",
        "ə",
        "r"
      ],
      "meaning": "tài xế",
      "emoji": "🚕",
      "topic": "grade4",
      "audio_sample_url": ""
    },
    {
      "word": "English",
      "ipa": "/ˈɪŋlɪʃ/",
      "phonemes": [
        "ɪ",
        "ŋ",
        "l",
        "ɪ",
        "ʃ"
      ],
      "meaning": "môn Tiếng Anh",
      "emoji": "📚",
      "topic": "grade4",
      "audio_sample_url": ""
    },
    {
      "word": "evening",
      "ipa": "/ˈivnɪŋ/",
      "phonemes": [
        "i",
        "v",
        "n",
        "ɪ",
        "ŋ"
      ],
      "meaning": "buổi tối",
      "emoji": "🗓️",
      "topic": "grade4",
      "audio_sample_url": ""
    },
    {
      "word": "farmer",
      "ipa": "/ˈfɑrmər/",
      "phonemes": [
        "f",
        "ɑ",
        "r",
        "m",
        "ə",
        "r"
      ],
      "meaning": "nông dân",
      "emoji": "🧑‍🌾",
      "topic": "grade4",
      "audio_sample_url": ""
    },
    {
      "word": "flat",
      "ipa": "/flæt/",
      "phonemes": [
        "f",
        "l",
        "æ",
        "t"
      ],
      "meaning": "căn hộ",
      "emoji": "🏢",
      "topic": "grade4",
      "audio_sample_url": ""
    },
    {
      "word": "football",
      "ipa": "/ˈfʊtˌbɔl/",
      "phonemes": [
        "f",
        "ʊ",
        "t",
        "b",
        "ɔ",
        "l"
      ],
      "meaning": "bóng đá",
      "emoji": "⚽",
      "topic": "grade4",
      "audio_sample_url": ""
    },
    {
      "word": "friday",
      "ipa": "/ˈfraɪˌdeɪ/",
      "phonemes": [
        "f",
        "r",
        "aɪ",
        "d",
        "eɪ"
      ],
      "meaning": "thứ Sáu",
      "emoji": "🗓️",
      "topic": "grade4",
      "audio_sample_url": ""
    },
    {
      "word": "friend",
      "ipa": "/frɛnd/",
      "phonemes": [
        "f",
        "r",
        "ɛ",
        "n",
        "d"
      ],
      "meaning": "bạn bè",
      "emoji": "💬",
      "topic": "grade4",
      "audio_sample_url": ""
    },
    {
      "word": "get up",
      "ipa": "/gɪt əp/",
      "phonemes": [
        "g",
        "ɪ",
        "t",
        "ə",
        "p"
      ],
      "meaning": "thức dậy",
      "emoji": "✅",
      "topic": "grade4",
      "audio_sample_url": ""
    },
    {
      "word": "go home",
      "ipa": "/goʊ hoʊm/",
      "phonemes": [
        "g",
        "oʊ",
        "h",
        "oʊ",
        "m"
      ],
      "meaning": "về nhà",
      "emoji": "🏙️",
      "topic": "grade4",
      "audio_sample_url": ""
    },
    {
      "word": "go shopping",
      "ipa": "/goʊ ˈʃɑpɪŋ/",
      "phonemes": [
        "g",
        "oʊ",
        "ʃ",
        "ɑ",
        "p",
        "ɪ",
        "ŋ"
      ],
      "meaning": "đi mua sắm",
      "emoji": "🛒",
      "topic": "grade4",
      "audio_sample_url": ""
    },
    {
      "word": "go to bed",
      "ipa": "/goʊ tɪ bɛd/",
      "phonemes": [
        "g",
        "oʊ",
        "t",
        "ɪ",
        "b",
        "ɛ",
        "d"
      ],
      "meaning": "đi ngủ",
      "emoji": "🧰",
      "topic": "grade4",
      "audio_sample_url": ""
    },
    {
      "word": "go to school",
      "ipa": "/goʊ tɪ skul/",
      "phonemes": [
        "g",
        "oʊ",
        "t",
        "ɪ",
        "s",
        "k",
        "u",
        "l"
      ],
      "meaning": "đi học",
      "emoji": "📚",
      "topic": "grade4",
      "audio_sample_url": ""
    },
    {
      "word": "gym",
      "ipa": "/ʤɪm/",
      "phonemes": [
        "ʤ",
        "ɪ",
        "m"
      ],
      "meaning": "phòng thể dục",
      "emoji": "🏋️",
      "topic": "grade4",
      "audio_sample_url": ""
    },
    {
      "word": "handsome",
      "ipa": "/ˈhænsəm/",
      "phonemes": [
        "h",
        "æ",
        "n",
        "s",
        "ə",
        "m"
      ],
      "meaning": "đẹp trai",
      "emoji": "🙂",
      "topic": "grade4",
      "audio_sample_url": ""
    },
    {
      "word": "have breakfast",
      "ipa": "/hæv ˈbrɛkfəst/",
      "phonemes": [
        "h",
        "æ",
        "v",
        "b",
        "r",
        "ɛ",
        "k",
        "f",
        "ə",
        "s",
        "t"
      ],
      "meaning": "ăn sáng",
      "emoji": "✅",
      "topic": "grade4",
      "audio_sample_url": ""
    },
    {
      "word": "history",
      "ipa": "/ˈhɪstəri/",
      "phonemes": [
        "h",
        "ɪ",
        "s",
        "t",
        "ə",
        "r",
        "i"
      ],
      "meaning": "môn Lịch sử",
      "emoji": "📚",
      "topic": "grade4",
      "audio_sample_url": ""
    },
    {
      "word": "holiday",
      "ipa": "/ˈhɑlɪˌdeɪ/",
      "phonemes": [
        "h",
        "ɑ",
        "l",
        "ɪ",
        "d",
        "eɪ"
      ],
      "meaning": "kỳ nghỉ",
      "emoji": "🎉",
      "topic": "grade4",
      "audio_sample_url": ""
    },
    {
      "word": "hot",
      "ipa": "/hɑt/",
      "phonemes": [
        "h",
        "ɑ",
        "t"
      ],
      "meaning": "nóng",
      "emoji": "🌦️",
      "topic": "grade4",
      "audio_sample_url": ""
    },
    {
      "word": "house",
      "ipa": "/haʊs/",
      "phonemes": [
        "h",
        "aʊ",
        "s"
      ],
      "meaning": "ngôi nhà",
      "emoji": "🏠",
      "topic": "grade4",
      "audio_sample_url": ""
    },
    {
      "word": "Japan",
      "ipa": "/ʤəˈpæn/",
      "phonemes": [
        "ʤ",
        "ə",
        "p",
        "æ",
        "n"
      ],
      "meaning": "Nhật Bản",
      "emoji": "🌏",
      "topic": "grade4",
      "audio_sample_url": ""
    },
    {
      "word": "kangaroo",
      "ipa": "/ˌkæŋgərˈu/",
      "phonemes": [
        "k",
        "æ",
        "ŋ",
        "g",
        "ə",
        "r",
        "u"
      ],
      "meaning": "chuột túi",
      "emoji": "🦘",
      "topic": "grade4",
      "audio_sample_url": ""
    },
    {
      "word": "library",
      "ipa": "/ˈlaɪbrɛˌri/",
      "phonemes": [
        "l",
        "aɪ",
        "b",
        "r",
        "ɛ",
        "r",
        "i"
      ],
      "meaning": "thư viện",
      "emoji": "🏛️",
      "topic": "grade4",
      "audio_sample_url": ""
    },
    {
      "word": "listen to music",
      "ipa": "/ˈlɪsən tɪ mˈjuzɪk/",
      "phonemes": [
        "l",
        "ɪ",
        "s",
        "ə",
        "n",
        "t",
        "ɪ",
        "m",
        "j",
        "u",
        "z",
        "ɪ",
        "k"
      ],
      "meaning": "nghe nhạc",
      "emoji": "🎵",
      "topic": "grade4",
      "audio_sample_url": ""
    },
    {
      "word": "Malaysia",
      "ipa": "/məˈleɪʒə/",
      "phonemes": [
        "m",
        "ə",
        "l",
        "eɪ",
        "ʒ",
        "ə"
      ],
      "meaning": "Ma-lai-xi-a",
      "emoji": "🌏",
      "topic": "grade4",
      "audio_sample_url": ""
    },
    {
      "word": "market",
      "ipa": "/ˈmɑrkɪt/",
      "phonemes": [
        "m",
        "ɑ",
        "r",
        "k",
        "ɪ",
        "t"
      ],
      "meaning": "chợ",
      "emoji": "🏪",
      "topic": "grade4",
      "audio_sample_url": ""
    },
    {
      "word": "maths",
      "ipa": "/maths*/",
      "phonemes": [
        "m",
        "a",
        "t",
        "h",
        "s",
        "*"
      ],
      "meaning": "môn Toán",
      "emoji": "📚",
      "topic": "grade4",
      "audio_sample_url": ""
    },
    {
      "word": "monday",
      "ipa": "/ˈmənˌdeɪ/",
      "phonemes": [
        "m",
        "ə",
        "n",
        "d",
        "eɪ"
      ],
      "meaning": "thứ Hai",
      "emoji": "🗓️",
      "topic": "grade4",
      "audio_sample_url": ""
    },
    {
      "word": "morning",
      "ipa": "/ˈmɔrnɪŋ/",
      "phonemes": [
        "m",
        "ɔ",
        "r",
        "n",
        "ɪ",
        "ŋ"
      ],
      "meaning": "buổi sáng",
      "emoji": "🌅",
      "topic": "grade4",
      "audio_sample_url": ""
    },
    {
      "word": "mountain",
      "ipa": "/ˈmaʊntən/",
      "phonemes": [
        "m",
        "aʊ",
        "n",
        "t",
        "ə",
        "n"
      ],
      "meaning": "núi",
      "emoji": "⛰️",
      "topic": "grade4",
      "audio_sample_url": ""
    },
    {
      "word": "music",
      "ipa": "/mˈjuzɪk/",
      "phonemes": [
        "m",
        "j",
        "u",
        "z",
        "ɪ",
        "k"
      ],
      "meaning": "môn Âm nhạc",
      "emoji": "🎵",
      "topic": "grade4",
      "audio_sample_url": ""
    },
    {
      "word": "music room",
      "ipa": "/mˈjuzɪk rum/",
      "phonemes": [
        "m",
        "j",
        "u",
        "z",
        "ɪ",
        "k",
        "r",
        "u",
        "m"
      ],
      "meaning": "phòng âm nhạc",
      "emoji": "🎼",
      "topic": "grade4",
      "audio_sample_url": ""
    },
    {
      "word": "night",
      "ipa": "/naɪt/",
      "phonemes": [
        "n",
        "aɪ",
        "t"
      ],
      "meaning": "ban đêm",
      "emoji": "🌙",
      "topic": "grade4",
      "audio_sample_url": ""
    },
    {
      "word": "nurse",
      "ipa": "/nərs/",
      "phonemes": [
        "n",
        "ə",
        "r",
        "s"
      ],
      "meaning": "y tá",
      "emoji": "👩‍⚕️",
      "topic": "grade4",
      "audio_sample_url": ""
    },
    {
      "word": "old",
      "ipa": "/oʊld/",
      "phonemes": [
        "oʊ",
        "l",
        "d"
      ],
      "meaning": "già",
      "emoji": "🙂",
      "topic": "grade4",
      "audio_sample_url": ""
    },
    {
      "word": "party",
      "ipa": "/ˈpɑrti/",
      "phonemes": [
        "p",
        "ɑ",
        "r",
        "t",
        "i"
      ],
      "meaning": "bữa tiệc",
      "emoji": "🥳",
      "topic": "grade4",
      "audio_sample_url": ""
    },
    {
      "word": "PE",
      "ipa": "/pe*/",
      "phonemes": [
        "p",
        "e",
        "*"
      ],
      "meaning": "môn Thể dục",
      "emoji": "📚",
      "topic": "grade4",
      "audio_sample_url": ""
    },
    {
      "word": "pilot",
      "ipa": "/ˈpaɪlət/",
      "phonemes": [
        "p",
        "aɪ",
        "l",
        "ə",
        "t"
      ],
      "meaning": "phi công",
      "emoji": "🧑‍✈️",
      "topic": "grade4",
      "audio_sample_url": ""
    },
    {
      "word": "playground",
      "ipa": "/ˈpleɪˌgraʊnd/",
      "phonemes": [
        "p",
        "l",
        "eɪ",
        "g",
        "r",
        "aʊ",
        "n",
        "d"
      ],
      "meaning": "sân chơi",
      "emoji": "🛝",
      "topic": "grade4",
      "audio_sample_url": ""
    },
    {
      "word": "post office",
      "ipa": "/poʊst ˈɔfəs/",
      "phonemes": [
        "p",
        "oʊ",
        "s",
        "t",
        "ɔ",
        "f",
        "ə",
        "s"
      ],
      "meaning": "bưu điện",
      "emoji": "🏤",
      "topic": "grade4",
      "audio_sample_url": ""
    },
    {
      "word": "present",
      "ipa": "/ˈprɛzənt/",
      "phonemes": [
        "p",
        "r",
        "ɛ",
        "z",
        "ə",
        "n",
        "t"
      ],
      "meaning": "quà tặng",
      "emoji": "🎁",
      "topic": "grade4",
      "audio_sample_url": ""
    },
    {
      "word": "rainy",
      "ipa": "/ˈreɪni/",
      "phonemes": [
        "r",
        "eɪ",
        "n",
        "i"
      ],
      "meaning": "có mưa",
      "emoji": "🌧️",
      "topic": "grade4",
      "audio_sample_url": ""
    },
    {
      "word": "read books",
      "ipa": "/rɛd bʊks/",
      "phonemes": [
        "r",
        "ɛ",
        "d",
        "b",
        "ʊ",
        "k",
        "s"
      ],
      "meaning": "đọc sách",
      "emoji": "📚",
      "topic": "grade4",
      "audio_sample_url": ""
    },
    {
      "word": "ride a bike",
      "ipa": "/raɪd ə baɪk/",
      "phonemes": [
        "r",
        "aɪ",
        "d",
        "ə",
        "b",
        "aɪ",
        "k"
      ],
      "meaning": "đạp xe",
      "emoji": "🚗",
      "topic": "grade4",
      "audio_sample_url": ""
    },
    {
      "word": "saturday",
      "ipa": "/ˈsæˌtɪˌdeɪ/",
      "phonemes": [
        "s",
        "æ",
        "t",
        "ɪ",
        "d",
        "eɪ"
      ],
      "meaning": "thứ Bảy",
      "emoji": "🗓️",
      "topic": "grade4",
      "audio_sample_url": ""
    },
    {
      "word": "science",
      "ipa": "/saɪəns/",
      "phonemes": [
        "s",
        "aɪ",
        "ə",
        "n",
        "s"
      ],
      "meaning": "môn Khoa học",
      "emoji": "📚",
      "topic": "grade4",
      "audio_sample_url": ""
    },
    {
      "word": "shopping centre",
      "ipa": "/ˈʃɑpɪŋ ˈsɛntər/",
      "phonemes": [
        "ʃ",
        "ɑ",
        "p",
        "ɪ",
        "ŋ",
        "s",
        "ɛ",
        "n",
        "t",
        "ə",
        "r"
      ],
      "meaning": "trung tâm mua sắm",
      "emoji": "🏬",
      "topic": "grade4",
      "audio_sample_url": ""
    },
    {
      "word": "short",
      "ipa": "/ʃɔrt/",
      "phonemes": [
        "ʃ",
        "ɔ",
        "r",
        "t"
      ],
      "meaning": "thấp",
      "emoji": "🙂",
      "topic": "grade4",
      "audio_sample_url": ""
    },
    {
      "word": "sing",
      "ipa": "/sɪŋ/",
      "phonemes": [
        "s",
        "ɪ",
        "ŋ"
      ],
      "meaning": "hát",
      "emoji": "🎵",
      "topic": "grade4",
      "audio_sample_url": ""
    },
    {
      "word": "Singapore",
      "ipa": "/ˈsɪŋəˌpɔr/",
      "phonemes": [
        "s",
        "ɪ",
        "ŋ",
        "ə",
        "p",
        "ɔ",
        "r"
      ],
      "meaning": "Xin-ga-po",
      "emoji": "🌏",
      "topic": "grade4",
      "audio_sample_url": ""
    },
    {
      "word": "singer",
      "ipa": "/ˈsɪŋər/",
      "phonemes": [
        "s",
        "ɪ",
        "ŋ",
        "ə",
        "r"
      ],
      "meaning": "ca sĩ",
      "emoji": "🎤",
      "topic": "grade4",
      "audio_sample_url": ""
    },
    {
      "word": "skate",
      "ipa": "/skeɪt/",
      "phonemes": [
        "s",
        "k",
        "eɪ",
        "t"
      ],
      "meaning": "trượt patin",
      "emoji": "🛼",
      "topic": "grade4",
      "audio_sample_url": ""
    },
    {
      "word": "slim",
      "ipa": "/slɪm/",
      "phonemes": [
        "s",
        "l",
        "ɪ",
        "m"
      ],
      "meaning": "mảnh mai",
      "emoji": "🙂",
      "topic": "grade4",
      "audio_sample_url": ""
    },
    {
      "word": "snake",
      "ipa": "/sneɪk/",
      "phonemes": [
        "s",
        "n",
        "eɪ",
        "k"
      ],
      "meaning": "rắn",
      "emoji": "🐍",
      "topic": "grade4",
      "audio_sample_url": ""
    },
    {
      "word": "sports day",
      "ipa": "/spɔrts deɪ/",
      "phonemes": [
        "s",
        "p",
        "ɔ",
        "r",
        "t",
        "s",
        "d",
        "eɪ"
      ],
      "meaning": "ngày hội thể thao",
      "emoji": "🏃",
      "topic": "grade4",
      "audio_sample_url": ""
    },
    {
      "word": "street",
      "ipa": "/strit/",
      "phonemes": [
        "s",
        "t",
        "r",
        "i",
        "t"
      ],
      "meaning": "đường phố",
      "emoji": "🚗",
      "topic": "grade4",
      "audio_sample_url": ""
    },
    {
      "word": "strong",
      "ipa": "/strɔŋ/",
      "phonemes": [
        "s",
        "t",
        "r",
        "ɔ",
        "ŋ"
      ],
      "meaning": "khỏe",
      "emoji": "🙂",
      "topic": "grade4",
      "audio_sample_url": ""
    },
    {
      "word": "subject",
      "ipa": "/ˈsəbʤɪkt/",
      "phonemes": [
        "s",
        "ə",
        "b",
        "ʤ",
        "ɪ",
        "k",
        "t"
      ],
      "meaning": "môn học",
      "emoji": "📚",
      "topic": "grade4",
      "audio_sample_url": ""
    },
    {
      "word": "summer camp",
      "ipa": "/ˈsəmər kæmp/",
      "phonemes": [
        "s",
        "ə",
        "m",
        "ə",
        "r",
        "k",
        "æ",
        "m",
        "p"
      ],
      "meaning": "trại hè",
      "emoji": "🗓️",
      "topic": "grade4",
      "audio_sample_url": ""
    },
    {
      "word": "sunday",
      "ipa": "/ˈsənˌdi/",
      "phonemes": [
        "s",
        "ə",
        "n",
        "d",
        "i"
      ],
      "meaning": "Chủ nhật",
      "emoji": "🗓️",
      "topic": "grade4",
      "audio_sample_url": ""
    },
    {
      "word": "sunny",
      "ipa": "/ˈsəni/",
      "phonemes": [
        "s",
        "ə",
        "n",
        "i"
      ],
      "meaning": "có nắng",
      "emoji": "☀️",
      "topic": "grade4",
      "audio_sample_url": ""
    },
    {
      "word": "supermarket",
      "ipa": "/ˈsupərˌmɑrkɪt/",
      "phonemes": [
        "s",
        "u",
        "p",
        "ə",
        "r",
        "m",
        "ɑ",
        "r",
        "k",
        "ɪ",
        "t"
      ],
      "meaning": "siêu thị",
      "emoji": "🛒",
      "topic": "grade4",
      "audio_sample_url": ""
    },
    {
      "word": "swim",
      "ipa": "/swɪm/",
      "phonemes": [
        "s",
        "w",
        "ɪ",
        "m"
      ],
      "meaning": "bơi",
      "emoji": "🏃",
      "topic": "grade4",
      "audio_sample_url": ""
    },
    {
      "word": "table tennis",
      "ipa": "/ˈteɪbəl ˈtɛnɪs/",
      "phonemes": [
        "t",
        "eɪ",
        "b",
        "ə",
        "l",
        "t",
        "ɛ",
        "n",
        "ɪ",
        "s"
      ],
      "meaning": "bóng bàn",
      "emoji": "🏓",
      "topic": "grade4",
      "audio_sample_url": ""
    },
    {
      "word": "tall",
      "ipa": "/tɔl/",
      "phonemes": [
        "t",
        "ɔ",
        "l"
      ],
      "meaning": "cao",
      "emoji": "🙂",
      "topic": "grade4",
      "audio_sample_url": ""
    },
    {
      "word": "teacher",
      "ipa": "/ˈtiʧər/",
      "phonemes": [
        "t",
        "i",
        "ʧ",
        "ə",
        "r"
      ],
      "meaning": "giáo viên",
      "emoji": "🧑‍🏫",
      "topic": "grade4",
      "audio_sample_url": ""
    },
    {
      "word": "tent",
      "ipa": "/tɛnt/",
      "phonemes": [
        "t",
        "ɛ",
        "n",
        "t"
      ],
      "meaning": "lều",
      "emoji": "⛺",
      "topic": "grade4",
      "audio_sample_url": ""
    },
    {
      "word": "Thailand",
      "ipa": "/ˈtaɪˌlænd/",
      "phonemes": [
        "t",
        "aɪ",
        "l",
        "æ",
        "n",
        "d"
      ],
      "meaning": "Thái Lan",
      "emoji": "🌏",
      "topic": "grade4",
      "audio_sample_url": ""
    },
    {
      "word": "thursday",
      "ipa": "/ˈθərzˌdeɪ/",
      "phonemes": [
        "θ",
        "ə",
        "r",
        "z",
        "d",
        "eɪ"
      ],
      "meaning": "thứ Năm",
      "emoji": "🗓️",
      "topic": "grade4",
      "audio_sample_url": ""
    },
    {
      "word": "timetable",
      "ipa": "/ˈtaɪmˌteɪbəl/",
      "phonemes": [
        "t",
        "aɪ",
        "m",
        "t",
        "eɪ",
        "b",
        "ə",
        "l"
      ],
      "meaning": "thời khóa biểu",
      "emoji": "📅",
      "topic": "grade4",
      "audio_sample_url": ""
    },
    {
      "word": "tuesday",
      "ipa": "/ˈtuzˌdeɪ/",
      "phonemes": [
        "t",
        "u",
        "z",
        "d",
        "eɪ"
      ],
      "meaning": "thứ Ba",
      "emoji": "🗓️",
      "topic": "grade4",
      "audio_sample_url": ""
    },
    {
      "word": "Viet Nam",
      "ipa": "/viɛt næm/",
      "phonemes": [
        "v",
        "i",
        "ɛ",
        "t",
        "n",
        "æ",
        "m"
      ],
      "meaning": "Việt Nam",
      "emoji": "🌏",
      "topic": "grade4",
      "audio_sample_url": ""
    },
    {
      "word": "Vietnamese",
      "ipa": "/viˌɛtnɑˈmis/",
      "phonemes": [
        "v",
        "i",
        "ɛ",
        "t",
        "n",
        "ɑ",
        "m",
        "i",
        "s"
      ],
      "meaning": "môn Tiếng Việt",
      "emoji": "📚",
      "topic": "grade4",
      "audio_sample_url": ""
    },
    {
      "word": "village",
      "ipa": "/ˈvɪlɪʤ/",
      "phonemes": [
        "v",
        "ɪ",
        "l",
        "ɪ",
        "ʤ"
      ],
      "meaning": "ngôi làng",
      "emoji": "🏘️",
      "topic": "grade4",
      "audio_sample_url": ""
    },
    {
      "word": "visit grandparents",
      "ipa": "/ˈvɪzɪt ˈgrændˌpɛrənts/",
      "phonemes": [
        "v",
        "ɪ",
        "z",
        "ɪ",
        "t",
        "g",
        "r",
        "æ",
        "n",
        "d",
        "p",
        "ɛ",
        "r",
        "ə",
        "n",
        "t",
        "s"
      ],
      "meaning": "thăm ông bà",
      "emoji": "👨‍👩‍👧‍👦",
      "topic": "grade4",
      "audio_sample_url": ""
    },
    {
      "word": "watch TV",
      "ipa": "/wɔʧ ˌtɛləˈvɪʒən/",
      "phonemes": [
        "w",
        "ɔ",
        "ʧ",
        "t",
        "ɛ",
        "l",
        "ə",
        "v",
        "ɪ",
        "ʒ",
        "ə",
        "n"
      ],
      "meaning": "xem ti vi",
      "emoji": "✅",
      "topic": "grade4",
      "audio_sample_url": ""
    },
    {
      "word": "weather",
      "ipa": "/ˈwɛðər/",
      "phonemes": [
        "w",
        "ɛ",
        "ð",
        "ə",
        "r"
      ],
      "meaning": "thời tiết",
      "emoji": "🌦️",
      "topic": "grade4",
      "audio_sample_url": ""
    },
    {
      "word": "wednesday",
      "ipa": "/ˈwɛnzˌdeɪ/",
      "phonemes": [
        "w",
        "ɛ",
        "n",
        "z",
        "d",
        "eɪ"
      ],
      "meaning": "thứ Tư",
      "emoji": "🗓️",
      "topic": "grade4",
      "audio_sample_url": ""
    },
    {
      "word": "windy",
      "ipa": "/ˈwɪndi/",
      "phonemes": [
        "w",
        "ɪ",
        "n",
        "d",
        "i"
      ],
      "meaning": "có gió",
      "emoji": "💨",
      "topic": "grade4",
      "audio_sample_url": ""
    },
    {
      "word": "worker",
      "ipa": "/ˈwərkər/",
      "phonemes": [
        "w",
        "ə",
        "r",
        "k",
        "ə",
        "r"
      ],
      "meaning": "công nhân",
      "emoji": "👷",
      "topic": "grade4",
      "audio_sample_url": ""
    },
    {
      "word": "young",
      "ipa": "/jəŋ/",
      "phonemes": [
        "j",
        "ə",
        "ŋ"
      ],
      "meaning": "trẻ",
      "emoji": "🙂",
      "topic": "grade4",
      "audio_sample_url": ""
    }
  ]
}