{
  "topicId": "t-f6fd97168f",
  "label": "Đồ ăn và đồ uống",
  "words": [
    {
      "word": "apple",
      "ipa": "/ˈæpəl/",
      "phonemes": [
        "æ",
        "p",
        "ə",
        "l"
      ],
      "meaning": "quả táo",
      "emoji": "🍎",
      "topic": "Đồ ăn và đồ uống",
      "topicId": "t-f6fd97168f",
      "grade": 1,
      "source": "grade1",
      "audio_sample_url": ""
    },
    {
      "word": "bakery",
      "ipa": "/ˈbeɪkəri/",
      "phonemes": [
        "b",
        "eɪ",
        "k",
        "ə",
        "r",
        "i"
      ],
      "meaning": "tiệm bánh",
      "emoji": "🥐",
      "topic": "Đồ ăn và đồ uống",
      "topicId": "t-f6fd97168f",
      "grade": 6,
      "source": "grade6",
      "audio_sample_url": ""
    },
    {
      "word": "banana",
      "ipa": "/bəˈnænə/",
      "phonemes": [
        "b",
        "ə",
        "n",
        "æ",
        "n",
        "ə"
      ],
      "meaning": "quả chuối",
      "emoji": "🍌",
      "topic": "Đồ ăn và đồ uống",
      "topicId": "t-f6fd97168f",
      "grade": 1,
      "source": "grade1",
      "audio_sample_url": ""
    },
    {
      "word": "bread",
      "ipa": "/brɛd/",
      "phonemes": [
        "b",
        "r",
        "ɛ",
        "d"
      ],
      "meaning": "bánh mì",
      "emoji": "🍞",
      "topic": "Đồ ăn và đồ uống",
      "topicId": "t-f6fd97168f",
      "grade": 2,
      "source": "grade2",
      "audio_sample_url": ""
    },
    {
      "word": "butter",
      "ipa": "/ˈbətər/",
      "phonemes": [
        "b",
        "ə",
        "t",
        "ə",
        "r"
      ],
      "meaning": "bơ",
      "emoji": "🧈",
      "topic": "Đồ ăn và đồ uống",
      "topicId": "t-f6fd97168f",
      "grade": 2,
      "source": "grade2",
      "audio_sample_url": ""
    },
    {
      "word": "cake",
      "ipa": "/keɪk/",
      "phonemes": [
        "k",
        "eɪ",
        "k"
      ],
      "meaning": "bánh ngọt",
      "emoji": "🎂",
      "topic": "Đồ ăn và đồ uống",
      "topicId": "t-f6fd97168f",
      "grade": 1,
      "source": "grade1",
      "audio_sample_url": ""
    },
    {
      "word": "coffee",
      "ipa": "/ˈkɔfi/",
      "phonemes": [
        "k",
        "ɔ",
        "f",
        "i"
      ],
      "meaning": "cà phê",
      "emoji": "☕",
      "topic": "Đồ ăn và đồ uống",
      "topicId": "t-f6fd97168f",
      "grade": 2,
      "source": "grade2",
      "audio_sample_url": ""
    },
    {
      "word": "cooker",
      "ipa": "/ˈkʊkər/",
      "phonemes": [
        "k",
        "ʊ",
        "k",
        "ə",
        "r"
      ],
      "meaning": "nồi cơm điện",
      "emoji": "🍚",
      "topic": "Đồ ăn và đồ uống",
      "topicId": "t-f6fd97168f",
      "grade": 6,
      "source": "grade6",
      "audio_sample_url": ""
    },
    {
      "word": "cuisine",
      "ipa": "/kwɪˈzin/",
      "phonemes": [
        "k",
        "w",
        "ɪ",
        "z",
        "i",
        "n"
      ],
      "meaning": "ẩm thực",
      "emoji": "🍽️",
      "topic": "Đồ ăn và đồ uống",
      "topicId": "t-f6fd97168f",
      "grade": 12,
      "source": "grade12",
      "audio_sample_url": ""
    },
    {
      "word": "egg",
      "ipa": "/ɛg/",
      "phonemes": [
        "ɛ",
        "g"
      ],
      "meaning": "trứng",
      "emoji": "🥚",
      "topic": "Đồ ăn và đồ uống",
      "topicId": "t-f6fd97168f",
      "grade": 2,
      "source": "grade2",
      "audio_sample_url": ""
    },
    {
      "word": "fatty food",
      "ipa": "/ˈfæti fud/",
      "phonemes": [
        "f",
        "æ",
        "t",
        "i",
        "f",
        "u",
        "d"
      ],
      "meaning": "đồ ăn nhiều dầu mỡ",
      "emoji": "🍽️",
      "topic": "Đồ ăn và đồ uống",
      "topicId": "t-f6fd97168f",
      "grade": 7,
      "source": "grade7",
      "audio_sample_url": ""
    },
    {
      "word": "food poisoning",
      "ipa": "/fud ˈpɔɪzənɪŋ/",
      "phonemes": [
        "f",
        "u",
        "d",
        "p",
        "ɔɪ",
        "z",
        "ə",
        "n",
        "ɪ",
        "ŋ"
      ],
      "meaning": "ngộ độc thực phẩm",
      "emoji": "🍽️",
      "topic": "Đồ ăn và đồ uống",
      "topicId": "t-f6fd97168f",
      "grade": 11,
      "source": "grade11",
      "audio_sample_url": ""
    },
    {
      "word": "fruit",
      "ipa": "/frut/",
      "phonemes": [
        "f",
        "r",
        "u",
        "t"
      ],
      "meaning": "trái cây",
      "emoji": "🍎",
      "topic": "Đồ ăn và đồ uống",
      "topicId": "t-f6fd97168f",
      "grade": 5,
      "source": "grade5",
      "audio_sample_url": ""
    },
    {
      "word": "grapes",
      "ipa": "/greɪps/",
      "phonemes": [
        "g",
        "r",
        "eɪ",
        "p",
        "s"
      ],
      "meaning": "nho",
      "emoji": "🍇",
      "topic": "Đồ ăn và đồ uống",
      "topicId": "t-f6fd97168f",
      "grade": 2,
      "source": "grade2",
      "audio_sample_url": ""
    },
    {
      "word": "grocery",
      "ipa": "/ˈgroʊsəri/",
      "phonemes": [
        "g",
        "r",
        "oʊ",
        "s",
        "ə",
        "r",
        "i"
      ],
      "meaning": "hàng tạp hóa",
      "emoji": "🍽️",
      "topic": "Đồ ăn và đồ uống",
      "topicId": "t-f6fd97168f",
      "grade": 10,
      "source": "grade10",
      "audio_sample_url": ""
    },
    {
      "word": "ingredient",
      "ipa": "/ˌɪnˈgridiənt/",
      "phonemes": [
        "ɪ",
        "n",
        "g",
        "r",
        "i",
        "d",
        "i",
        "ə",
        "n",
        "t"
      ],
      "meaning": "thành phần",
      "emoji": "🍽️",
      "topic": "Đồ ăn và đồ uống",
      "topicId": "t-f6fd97168f",
      "grade": 11,
      "source": "grade11",
      "audio_sample_url": ""
    },
    {
      "word": "item",
      "ipa": "/ˈaɪtəm/",
      "phonemes": [
        "aɪ",
        "t",
        "ə",
        "m"
      ],
      "meaning": "món hàng",
      "emoji": "🛍️",
      "topic": "Đồ ăn và đồ uống",
      "topicId": "t-f6fd97168f",
      "grade": 8,
      "source": "grade8",
      "audio_sample_url": ""
    },
    {
      "word": "jam",
      "ipa": "/ʤæm/",
      "phonemes": [
        "ʤ",
        "æ",
        "m"
      ],
      "meaning": "mứt",
      "emoji": "🍓",
      "topic": "Đồ ăn và đồ uống",
      "topicId": "t-f6fd97168f",
      "grade": 2,
      "source": "grade2",
      "audio_sample_url": ""
    },
    {
      "word": "jelly",
      "ipa": "/ˈʤɛli/",
      "phonemes": [
        "ʤ",
        "ɛ",
        "l",
        "i"
      ],
      "meaning": "thạch",
      "emoji": "🍮",
      "topic": "Đồ ăn và đồ uống",
      "topicId": "t-f6fd97168f",
      "grade": 2,
      "source": "grade2",
      "audio_sample_url": ""
    },
    {
      "word": "juice",
      "ipa": "/ʤus/",
      "phonemes": [
        "ʤ",
        "u",
        "s"
      ],
      "meaning": "nước ép",
      "emoji": "🧃",
      "topic": "Đồ ăn và đồ uống",
      "topicId": "t-f6fd97168f",
      "grade": 1,
      "source": "grade1",
      "audio_sample_url": ""
    },
    {
      "word": "lemon",
      "ipa": "/ˈlɛmən/",
      "phonemes": [
        "l",
        "ɛ",
        "m",
        "ə",
        "n"
      ],
      "meaning": "quả chanh",
      "emoji": "🍋",
      "topic": "Đồ ăn và đồ uống",
      "topicId": "t-f6fd97168f",
      "grade": 1,
      "source": "grade1",
      "audio_sample_url": ""
    },
    {
      "word": "menu",
      "ipa": "/ˈmɛnju/",
      "phonemes": [
        "m",
        "ɛ",
        "n",
        "j",
        "u"
      ],
      "meaning": "thực đơn",
      "emoji": "🍽️",
      "topic": "Đồ ăn và đồ uống",
      "topicId": "t-f6fd97168f",
      "grade": 2,
      "source": "grade2",
      "audio_sample_url": ""
    },
    {
      "word": "milk",
      "ipa": "/mɪlk/",
      "phonemes": [
        "m",
        "ɪ",
        "l",
        "k"
      ],
      "meaning": "sữa",
      "emoji": "🥛",
      "topic": "Đồ ăn và đồ uống",
      "topicId": "t-f6fd97168f",
      "grade": 1,
      "source": "grade1",
      "audio_sample_url": ""
    },
    {
      "word": "noodles",
      "ipa": "/ˈnudəlz/",
      "phonemes": [
        "n",
        "u",
        "d",
        "ə",
        "l",
        "z"
      ],
      "meaning": "mì",
      "emoji": "🍜",
      "topic": "Đồ ăn và đồ uống",
      "topicId": "t-f6fd97168f",
      "grade": 1,
      "source": "grade1",
      "audio_sample_url": ""
    },
    {
      "word": "nuts",
      "ipa": "/nəts/",
      "phonemes": [
        "n",
        "ə",
        "t",
        "s"
      ],
      "meaning": "các loại hạt",
      "emoji": "🥜",
      "topic": "Đồ ăn và đồ uống",
      "topicId": "t-f6fd97168f",
      "grade": 1,
      "source": "grade1",
      "audio_sample_url": ""
    },
    {
      "word": "omelette",
      "ipa": "/omelette*/",
      "phonemes": [
        "o",
        "m",
        "e",
        "l",
        "e",
        "t",
        "t",
        "e",
        "*"
      ],
      "meaning": "trứng ốp lết",
      "emoji": "🍳",
      "topic": "Đồ ăn và đồ uống",
      "topicId": "t-f6fd97168f",
      "grade": 7,
      "source": "grade7",
      "audio_sample_url": ""
    },
    {
      "word": "orange",
      "ipa": "/ˈɔrɪnʤ/",
      "phonemes": [
        "ɔ",
        "r",
        "ɪ",
        "n",
        "ʤ"
      ],
      "meaning": "quả cam",
      "emoji": "🍊",
      "topic": "Đồ ăn và đồ uống",
      "topicId": "t-f6fd97168f",
      "grade": 1,
      "source": "grade1",
      "audio_sample_url": ""
    },
    {
      "word": "pancake",
      "ipa": "/ˈpænˌkeɪk/",
      "phonemes": [
        "p",
        "æ",
        "n",
        "k",
        "eɪ",
        "k"
      ],
      "meaning": "bánh kếp",
      "emoji": "🥞",
      "topic": "Đồ ăn và đồ uống",
      "topicId": "t-f6fd97168f",
      "grade": 7,
      "source": "grade7",
      "audio_sample_url": ""
    },
    {
      "word": "pasta",
      "ipa": "/ˈpɑstə/",
      "phonemes": [
        "p",
        "ɑ",
        "s",
        "t",
        "ə"
      ],
      "meaning": "mì Ý",
      "emoji": "🍝",
      "topic": "Đồ ăn và đồ uống",
      "topicId": "t-f6fd97168f",
      "grade": 1,
      "source": "grade1",
      "audio_sample_url": ""
    },
    {
      "word": "pepper",
      "ipa": "/ˈpɛpər/",
      "phonemes": [
        "p",
        "ɛ",
        "p",
        "ə",
        "r"
      ],
      "meaning": "hạt tiêu",
      "emoji": "🌶️",
      "topic": "Đồ ăn và đồ uống",
      "topicId": "t-f6fd97168f",
      "grade": 7,
      "source": "grade7",
      "audio_sample_url": ""
    },
    {
      "word": "pizza",
      "ipa": "/ˈpitsə/",
      "phonemes": [
        "p",
        "i",
        "t",
        "s",
        "ə"
      ],
      "meaning": "bánh pizza",
      "emoji": "🍕",
      "topic": "Đồ ăn và đồ uống",
      "topicId": "t-f6fd97168f",
      "grade": 1,
      "source": "grade1",
      "audio_sample_url": ""
    },
    {
      "word": "popcorn",
      "ipa": "/ˈpɑpˌkɔrn/",
      "phonemes": [
        "p",
        "ɑ",
        "p",
        "k",
        "ɔ",
        "r",
        "n"
      ],
      "meaning": "bỏng ngô",
      "emoji": "🍿",
      "topic": "Đồ ăn và đồ uống",
      "topicId": "t-f6fd97168f",
      "grade": 1,
      "source": "grade1",
      "audio_sample_url": ""
    },
    {
      "word": "pork",
      "ipa": "/pɔrk/",
      "phonemes": [
        "p",
        "ɔ",
        "r",
        "k"
      ],
      "meaning": "thịt lợn",
      "emoji": "🍽️",
      "topic": "Đồ ăn và đồ uống",
      "topicId": "t-f6fd97168f",
      "grade": 7,
      "source": "grade7",
      "audio_sample_url": ""
    },
    {
      "word": "recipe",
      "ipa": "/ˈrɛsəpi/",
      "phonemes": [
        "r",
        "ɛ",
        "s",
        "ə",
        "p",
        "i"
      ],
      "meaning": "công thức nấu ăn",
      "emoji": "🍽️",
      "topic": "Đồ ăn và đồ uống",
      "topicId": "t-f6fd97168f",
      "grade": 11,
      "source": "grade11",
      "audio_sample_url": ""
    },
    {
      "word": "rice",
      "ipa": "/raɪs/",
      "phonemes": [
        "r",
        "aɪ",
        "s"
      ],
      "meaning": "cơm",
      "emoji": "🍚",
      "topic": "Đồ ăn và đồ uống",
      "topicId": "t-f6fd97168f",
      "grade": 1,
      "source": "grade1",
      "audio_sample_url": ""
    },
    {
      "word": "sandwich",
      "ipa": "/ˈsænwɪʧ/",
      "phonemes": [
        "s",
        "æ",
        "n",
        "w",
        "ɪ",
        "ʧ"
      ],
      "meaning": "bánh sandwich",
      "emoji": "🥪",
      "topic": "Đồ ăn và đồ uống",
      "topicId": "t-f6fd97168f",
      "grade": 2,
      "source": "grade2",
      "audio_sample_url": ""
    },
    {
      "word": "shrimp",
      "ipa": "/ʃrɪmp/",
      "phonemes": [
        "ʃ",
        "r",
        "ɪ",
        "m",
        "p"
      ],
      "meaning": "tôm",
      "emoji": "🍽️",
      "topic": "Đồ ăn và đồ uống",
      "topicId": "t-f6fd97168f",
      "grade": 7,
      "source": "grade7",
      "audio_sample_url": ""
    },
    {
      "word": "spring roll",
      "ipa": "/spərɪŋ roʊl/",
      "phonemes": [
        "s",
        "p",
        "ə",
        "r",
        "ɪ",
        "ŋ",
        "r",
        "oʊ",
        "l"
      ],
      "meaning": "nem rán",
      "emoji": "🥢",
      "topic": "Đồ ăn và đồ uống",
      "topicId": "t-f6fd97168f",
      "grade": 7,
      "source": "grade7",
      "audio_sample_url": ""
    },
    {
      "word": "sugar",
      "ipa": "/ˈʃʊgər/",
      "phonemes": [
        "ʃ",
        "ʊ",
        "g",
        "ə",
        "r"
      ],
      "meaning": "đường",
      "emoji": "🍬",
      "topic": "Đồ ăn và đồ uống",
      "topicId": "t-f6fd97168f",
      "grade": 2,
      "source": "grade2",
      "audio_sample_url": ""
    },
    {
      "word": "sweet soup",
      "ipa": "/swit sup/",
      "phonemes": [
        "s",
        "w",
        "i",
        "t",
        "s",
        "u",
        "p"
      ],
      "meaning": "chè",
      "emoji": "🍽️",
      "topic": "Đồ ăn và đồ uống",
      "topicId": "t-f6fd97168f",
      "grade": 7,
      "source": "grade7",
      "audio_sample_url": ""
    },
    {
      "word": "tea",
      "ipa": "/ti/",
      "phonemes": [
        "t",
        "i"
      ],
      "meaning": "trà",
      "emoji": "🍵",
      "topic": "Đồ ăn và đồ uống",
      "topicId": "t-f6fd97168f",
      "grade": 2,
      "source": "grade2",
      "audio_sample_url": ""
    },
    {
      "word": "tofu",
      "ipa": "/ˈtoʊfu/",
      "phonemes": [
        "t",
        "oʊ",
        "f",
        "u"
      ],
      "meaning": "đậu phụ",
      "emoji": "⬜",
      "topic": "Đồ ăn và đồ uống",
      "topicId": "t-f6fd97168f",
      "grade": 7,
      "source": "grade7",
      "audio_sample_url": ""
    },
    {
      "word": "turmeric",
      "ipa": "/turmeric*/",
      "phonemes": [
        "t",
        "u",
        "r",
        "m",
        "e",
        "r",
        "i",
        "c",
        "*"
      ],
      "meaning": "nghệ",
      "emoji": "🍽️",
      "topic": "Đồ ăn và đồ uống",
      "topicId": "t-f6fd97168f",
      "grade": 7,
      "source": "grade7",
      "audio_sample_url": ""
    },
    {
      "word": "vegetable",
      "ipa": "/ˈvɛʤtəbəl/",
      "phonemes": [
        "v",
        "ɛ",
        "ʤ",
        "t",
        "ə",
        "b",
        "ə",
        "l"
      ],
      "meaning": "rau củ",
      "emoji": "🥦",
      "topic": "Đồ ăn và đồ uống",
      "topicId": "t-f6fd97168f",
      "grade": 5,
      "source": "grade5",
      "audio_sample_url": ""
    },
    {
      "word": "yam",
      "ipa": "/jæm/",
      "phonemes": [
        "j",
        "æ",
        "m"
      ],
      "meaning": "khoai lang",
      "emoji": "🍽️",
      "topic": "Đồ ăn và đồ uống",
      "topicId": "t-f6fd97168f",
      "grade": 2,
      "source": "grade2",
      "audio_sample_url": ""
    },
    {
      "word": "yogurt",
      "ipa": "/ˈjoʊgərt/",
      "phonemes": [
        "j",
        "oʊ",
        "g",
        "ə",
        "r",
        "t"
      ],
      "meaning": "sữa chua",
      "emoji": "🥛",
      "topic": "Đồ ăn và đồ uống",
      "topicId": "t-f6fd97168f",
      "grade": 2,
      "source": "grade2",
      "audio_sample_url": ""
    }
  ]
}