[
  {
    "id": 1,
    "title": "Test 01",
    "file": "test01.json"
  },
  {
    "id": 2,
    "title": "Test 02",
    "file": "test02.json"
  },
  {
    "id": 3,
    "title": "Test 03",
    "file": "test03.json"
  },
  {
    "id": 4,
    "title": "Test 04",
    "file": "test04.json"
  },
  {
    "id": 5,
    "title": "Test 05",
    "file": "test05.json"
  },
  {
    "id": 6,
    "title": "Test 06",
    "file": "test06.json"
  },
  {
    "id": 7,
    "title": "Test 07",
    "file": "test07.json"
  },
  {
    "id": 8,
    "title": "Test 08",
    "file": "test08.json"
  },
  {
    "id": 9,
    "title": "Test 09",
    "file": "test09.json"
  },
  {
    "id": 10,
    "title": "Test 10",
    "file": "test10.json"
  }
]